{
  "date": "2026-04-03",
  "engineVersion": "Rubrics 1960 - 1960",
  "hour": "matutinum",
  "language": "la",
  "liturgicalTitle": "Feria Sexta in Passione et Morte Domini ~ I. classis",
  "rank": "Feria Sexta in Passione et Morte Domini;;Feria privilegiata Duplex I classis;;7\n\n",
  "schemaVersion": "0.1.0",
  "sourceRefs": [
    {
      "path": "web/cgi-bin/horas/horas.pl",
      "section": "getordinarium/specials/getunit/resolve_refs",
      "transformation": [
        "Divinum Officium internal script array exported before print_content"
      ],
      "upstreamCommit": "515a213f79951c563be4f599ca591c63aa63bb6d"
    }
  ],
  "units": [
    {
      "html": "Incipit{omittitur}<br/>\n",
      "id": "do-1962-2026-04-03-matutinum-001",
      "raw": "#Incipit{omittitur}\n"
    },
    {
      "html": "Invitatorium{omittitur}<br/>\n",
      "id": "do-1962-2026-04-03-matutinum-002",
      "raw": "#Invitatorium{omittitur}\n"
    },
    {
      "html": "Hymnus{omittitur}<br/>\n",
      "id": "do-1962-2026-04-03-matutinum-003",
      "raw": "#Hymnus{omittitur}\n"
    },
    {
      "html": "Psalmi cum lectionibus {Antiphonæ et Psalmi ex Proprio de Tempore}\n<br/>\nNocturnus I<br/>\nAnt. Astitérunt reges terræ, * et príncipes convenérunt in unum, advérsus Dóminum, et advérsus Christum ejus.<br/>\nPsalmus 2 [1]<br/>\n2:1 Quare fremuérunt gentes: * et pópuli meditáti sunt inánia?<br/>\n2:2 Astitérunt reges terræ, et príncipes convenérunt in unum * advérsus Dóminum, et advérsus Christum ejus.<br/>\n2:3 Dirumpámus víncula eórum: * et proiciámus a nobis jugum ipsórum.<br/>\n2:4 Qui hábitat in cælis, irridébit eos: * et Dóminus subsannábit eos.<br/>\n2:5 Tunc loquétur ad eos in ira sua, * et in furóre suo conturbábit eos.<br/>\n2:6 Ego autem constitútus sum Rex ab eo super Sion montem sanctum ejus, * prǽdicans præcéptum ejus.<br/>\n2:7 Dóminus dixit ad me: * Fílius meus es tu, ego hódie génui te.<br/>\n2:8 Póstula a me, et dabo tibi gentes hereditátem tuam, * et possessiónem tuam términos terræ.<br/>\n2:9 Reges eos in virga férrea, * et tamquam vas fíguli confrínges eos.<br/>\n2:10 Et nunc, reges, intellégite: * erudímini, qui judicátis terram.<br/>\n2:11 Servíte Dómino in timóre: * et exsultáte ei cum tremóre.<br/>\n2:12 Apprehéndite disciplínam, nequándo irascátur Dóminus, * et pereátis de via justa.<br/>\n2:13 Cum exárserit in brevi ira ejus: * beáti omnes qui confídunt in eo.<br/>\nGloria omittitur<br/>\nAnt. Astitérunt reges terræ, et príncipes convenérunt in unum, advérsus Dóminum, et advérsus Christum ejus.<br/>\n",
      "id": "do-1962-2026-04-03-matutinum-004",
      "raw": "#Psalmi cum lectionibus{Antiphonæ et Psalmi ex Proprio de Tempore}\n!Nocturnus I\nAnt. Astitérunt reges terræ, * et príncipes convenérunt in unum, advérsus Dóminum, et advérsus Christum ejus.\n&psalm(2)\nAnt. Astitérunt reges terræ, et príncipes convenérunt in unum, advérsus Dóminum, et advérsus Christum ejus.\n"
    },
    {
      "html": "Ant. Divisérunt sibi * vestiménta mea, et super vestem meam misérunt sortem.<br/>\nPsalmus 21 [2]<br/>\n21:2 Deus, Deus meus, réspice in me: quare me dereliquísti? * longe a salúte mea verba delictórum meórum.<br/>\n21:3 Deus meus, clamábo per diem, et non exáudies: * et nocte, et non ad insipiéntiam mihi.<br/>\n21:4 Tu autem in sancto hábitas, * laus Israël.<br/>\n21:5 In te speravérunt patres nostri: * speravérunt, et liberásti eos.<br/>\n21:6 Ad te clamavérunt, et salvi facti sunt: * in te speravérunt, et non sunt confúsi.<br/>\n21:7 Ego autem sum vermis, et non homo: * oppróbrium hóminum, et abjéctio plebis.<br/>\n21:8 Omnes vidéntes me, derisérunt me: * locúti sunt lábiis, et movérunt caput.<br/>\n21:9 Sperávit in Dómino, erípiat eum: * salvum fáciat eum, quóniam vult eum.<br/>\n21:10 Quóniam tu es, qui extraxísti me de ventre: * spes mea ab ubéribus matris meæ. In te projéctus sum ex útero:<br/>\n21:11 De ventre matris meæ Deus meus es tu, * ne discésseris a me:<br/>\n21:12 Quóniam tribulátio próxima est: * quóniam non est qui ádjuvet.<br/>\n21:13 Circumdedérunt me vítuli multi: * tauri pingues obsedérunt me.<br/>\n21:14 Aperuérunt super me os suum, * sicut leo rápiens et rúgiens.<br/>\n21:15 Sicut aqua effúsus sum: * et dispérsa sunt ómnia ossa mea.<br/>\n21:15 Factum est cor meum tamquam cera liquéscens * in médio ventris mei.<br/>\n21:16 Áruit tamquam testa virtus mea, et lingua mea adhǽsit fáucibus meis: * et in púlverem mortis deduxísti me.<br/>\n21:17 Quóniam circumdedérunt me canes multi: * concílium malignántium obsédit me.<br/>\n21:17 Fodérunt manus meas et pedes meos: * dinumeravérunt ómnia ossa mea.<br/>\n21:18 Ipsi vero consideravérunt et inspexérunt me: * divisérunt sibi vestiménta mea, et super vestem meam misérunt sortem.<br/>\n21:20 Tu autem, Dómine, ne elongáveris auxílium tuum a me: * ad defensiónem meam cónspice.<br/>\n21:21 Érue a frámea, Deus, ánimam meam: * et de manu canis únicam meam:<br/>\n21:22 Salva me ex ore leónis: * et a córnibus unicórnium humilitátem meam.<br/>\n21:23 Narrábo nomen tuum frátribus meis: * in médio ecclésiæ laudábo te.<br/>\n21:24 Qui timétis Dóminum, laudáte eum: * univérsum semen Jacob, glorificáte eum.<br/>\n21:25 Tímeat eum omne semen Israël: * quóniam non sprevit, neque despéxit deprecatiónem páuperis:<br/>\n21:25 Nec avértit fáciem suam a me: * et cum clamárem ad eum, exaudívit me.<br/>\n21:26 Apud te laus mea in ecclésia magna: * vota mea reddam in conspéctu timéntium eum.<br/>\n21:27 Edent páuperes, et saturabúntur: et laudábunt Dóminum qui requírunt eum: * vivent corda eórum in sǽculum sǽculi.<br/>\n21:28 Reminiscéntur et converténtur ad Dóminum * univérsi fines terræ:<br/>\n21:28 Et adorábunt in conspéctu ejus * univérsæ famíliæ géntium.<br/>\n21:29 Quóniam Dómini est regnum: * et ipse dominábitur géntium.<br/>\n21:30 Manducavérunt et adoravérunt omnes pingues terræ: * in conspéctu ejus cadent omnes qui descéndunt in terram.<br/>\n21:31 Et ánima mea illi vivet: * et semen meum sérviet ipsi.<br/>\n21:32 Annuntiábitur Dómino generátio ventúra: * et annuntiábunt cæli justítiam ejus pópulo qui nascétur, quem fecit Dóminus.<br/>\nGloria omittitur<br/>\nAnt. Divisérunt sibi vestiménta mea, et super vestem meam misérunt sortem.<br/>\n",
      "id": "do-1962-2026-04-03-matutinum-005",
      "raw": "Ant. Divisérunt sibi * vestiménta mea, et super vestem meam misérunt sortem.\n&psalm(21)\nAnt. Divisérunt sibi vestiménta mea, et super vestem meam misérunt sortem.\n"
    },
    {
      "html": "Ant. Insurrexérunt in me * testes iníqui, et mentíta est iníquitas sibi.<br/>\nPsalmus 26 [3]<br/>\n26:1 Dóminus illuminátio mea, et salus mea, * quem timébo?<br/>\n26:1 Dóminus protéctor vitæ meæ, * a quo trepidábo?<br/>\n26:2 Dum apprópiant super me nocéntes, * ut edant carnes meas:<br/>\n26:2 Qui tríbulant me inimíci mei, * ipsi infirmáti sunt, et cecidérunt.<br/>\n26:3 Si consístant advérsum me castra, * non timébit cor meum.<br/>\n26:3 Si exsúrgat advérsum me prǽlium, * in hoc ego sperábo.<br/>\n26:4 Unam pétii a Dómino, hanc requíram, * ut inhábitem in domo Dómini ómnibus diébus vitæ meæ:<br/>\n26:4 Ut vídeam voluptátem Dómini, * et vísitem templum ejus.<br/>\n26:5 Quóniam abscóndit me in tabernáculo suo: * in die malórum protéxit me in abscóndito tabernáculi sui.<br/>\n26:6 In petra exaltávit me: * et nunc exaltávit caput meum super inimícos meos.<br/>\n26:6 Circuívi, et immolávi in tabernáculo ejus hóstiam vociferatiónis: * cantábo, et psalmum dicam Dómino.<br/>\n26:7 Exáudi, Dómine, vocem meam, qua clamávi ad te: * miserére mei, et exáudi me.<br/>\n26:8 Tibi dixit cor meum, exquisívit te fácies mea: * fáciem tuam, Dómine, requíram.<br/>\n26:9 Ne avértas fáciem tuam a me: * ne declínes in ira a servo tuo.<br/>\n26:9 Adjútor meus esto: * ne derelínquas me, neque despícias me, Deus, salutáris meus.<br/>\n26:10 Quóniam pater meus, et mater mea dereliquérunt me: * Dóminus autem assúmpsit me.<br/>\n26:11 Legem pone mihi, Dómine, in via tua: * et dírige me in sémitam rectam propter inimícos meos.<br/>\n26:12 Ne tradíderis me in ánimas tribulántium me: * quóniam insurrexérunt in me testes iníqui, et mentíta est iníquitas sibi.<br/>\n26:13 Credo vidére bona Dómini * in terra vivéntium.<br/>\n26:14 Exspécta Dóminum, viríliter age: * et confortétur cor tuum, et sústine Dóminum.<br/>\nGloria omittitur<br/>\nAnt. Insurrexérunt in me testes iníqui, et mentíta est iníquitas sibi.<br/>\n",
      "id": "do-1962-2026-04-03-matutinum-006",
      "raw": "Ant. Insurrexérunt in me * testes iníqui, et mentíta est iníquitas sibi.\n&psalm(26)\nAnt. Insurrexérunt in me testes iníqui, et mentíta est iníquitas sibi.\n"
    },
    {
      "html": "℣. Divisérunt sibi vestiménta mea.<br/>\n℟. Et super vestem meam misérunt sortem.<br/>\n",
      "id": "do-1962-2026-04-03-matutinum-007",
      "raw": "V. Divisérunt sibi vestiménta mea.\nR. Et super vestem meam misérunt sortem.\n"
    },
    {
      "html": "<span class='nigra'>Pater Noster</span> dicitur totum secreto.<br/>\nPater noster, qui es in cælis, sanctificétur nomen tuum: advéniat regnum tuum: fiat volúntas tua, sicut in cælo et in terra. Panem nostrum cotidiánum da nobis hódie: et dimítte nobis débita nostra, sicut et nos dimíttimus debitóribus nostris: et ne nos indúcas in tentatiónem: sed líbera nos a malo. Amen.<br/>\n",
      "id": "do-1962-2026-04-03-matutinum-008",
      "raw": "$Pater totum secreto\n"
    },
    {
      "html": "<br/>\nLectio 1<br/>\nDe Lamentatióne Jeremíæ Prophétæ<br/>\nLam 2:8-11<br/>\n8 Heth. Cogitávit Dóminus dissipáre murum fíliæ Sion: teténdit funículum suum, et non avértit manum suam a perditióne: luxítque antemurále, et murus páriter dissipátus est.<br/>\n9 Teth. Defíxæ sunt in terra portæ ejus: pérdidit, et contrívit vectes ejus: regem ejus et príncipes ejus in géntibus: non est lex, et prophétæ ejus non invenérunt visiónem a Dómino.<br/>\n10 Jod. Sedérunt in terra, conticuérunt senes fíliæ Sion: conspersérunt cínere cápita sua, accíncti sunt cilíciis, abjecérunt in terram cápita sua vírgines Jerúsalem.<br/>\n11 Caph. Defecérunt præ lácrimis óculi mei, conturbáta sunt víscera mea: effúsum est in terra jecur meum super contritióne fíliæ pópuli mei, cum defíceret párvulus et lactens in platéis óppidi.<br/>\nJerúsalem, Jerúsalem, convértere ad Dóminum Deum tuum.<br/>\n_<br/>\n℟. Omnes amíci mei dereliquérunt me, et prævaluérunt insidiántes mihi: trádidit me quem diligébam:<br/>\n* Et terribílibus óculis plaga crudéli percutiéntes, acéto potábant me.<br/>\n℣. Inter iníquos projecérunt me, et non pepercérunt ánimæ meæ.<br/>\n℟. Et terribílibus óculis plaga crudéli percutiéntes, acéto potábant me.<br/>\n",
      "id": "do-1962-2026-04-03-matutinum-009",
      "raw": "&lectio(1)\n"
    },
    {
      "html": "<br/>\nLectio 2<br/>\nLam 2:12-15<br/>\n12 Lamed. Mátribus suis dixérunt: Ubi est tríticum et vinum? cum defícerent quasi vulneráti in platéis civitátis: cum exhalárent ánimas suas in sinu matrum suárum.<br/>\n13 Mem. Cui comparábo te? vel cui assimilábo te, fília Jerúsalem? cui exæquábo te, et consolábor te, virgo fília Sion? Magna est enim velut mare contrítio tua: quis medébitur tui?<br/>\n14 Nun. Prophétæ tui vidérunt tibi falsa et stulta, nec aperiébant iniquitátem tuam, ut te ad pœniténtiam provocárent: vidérunt autem tibi assumptiónes falsas, et ejectiónes.<br/>\n15 Samech. Plausérunt super te mánibus omnes transeúntes per viam: sibilavérunt, et movérunt caput suum super fíliam Jerúsalem: Hǽccine est urbs, dicéntes, perfécti decóris, gáudium univérsæ terræ?<br/>\nJerúsalem, Jerúsalem, convértere ad Dóminum Deum tuum.<br/>\n_<br/>\n℟. Velum templi scissum est,<br/>\n* Et omnis terra trémuit: latro de cruce clamábat, dicens: Meménto mei, Dómine, dum véneris in regnum tuum.<br/>\n℣. Petræ scissæ sunt, et monuménta apérta sunt, et multa córpora sanctórum, qui dormíerant, surrexérunt.<br/>\n℟. Et omnis terra trémuit: latro de cruce clamábat, dicens: Meménto mei, Dómine, dum véneris in regnum tuum.<br/>\n",
      "id": "do-1962-2026-04-03-matutinum-010",
      "raw": "&lectio(2)\n"
    },
    {
      "html": "<br/>\nLectio 3<br/>\nLam 3:1-9<br/>\n1 Aleph. Ego vir videns paupertátem meam in virga indignatiónis ejus.<br/>\n2 Aleph. Me minávit, et addúxit in ténebras, et non in lucem.<br/>\n3 Aleph. Tantum in me vertit, et convértit manum suam tota die.<br/>\n4 Beth. Vetústam fecit pellem meam, et carnem meam, contrívit ossa mea.<br/>\n5 Beth. Ædificávit in gyro meo, et circúmdedit me felle et labóre.<br/>\n6 Beth. In tenebrósis collocávit me, quasi mórtuos sempitérnos.<br/>\n7 Ghimel. Circumædificávit advérsum me, ut non egrédiar: aggravávit cómpedem meum.<br/>\n8 Ghimel. Sed et, cum clamávero et rogávero, exclúsit oratiónem meam.<br/>\n9 Ghimel. Conclúsit vias meas lapídibus quadris, sémitas meas subvértit.<br/>\nJerúsalem, Jerúsalem, convértere ad Dóminum Deum tuum.<br/>\n_<br/>\n℟. Vínea mea elécta, ego te plantávi:<br/>\n* Quómodo convérsa es in amaritúdinem, ut me crucifígeres et Barábbam dimítteres?<br/>\n℣. Sepívi te, et lápides elégi ex te, et ædificávi turrim.<br/>\n℟. Quómodo convérsa es in amaritúdinem, ut me crucifígeres et Barábbam dimítteres?<br/>\nGloria omittitur<br/>\n℟. Vínea mea elécta, ego te plantávi: * Quómodo convérsa es in amaritúdinem, ut me crucifígeres et Barábbam dimítteres?<br/>\n",
      "id": "do-1962-2026-04-03-matutinum-011",
      "raw": "&lectio(3)\n"
    },
    {
      "html": "Nocturnus II<br/>\nAnt. Vim faciébant, * qui quærébant ánimam meam.<br/>\nPsalmus 37 [4]<br/>\n37:2 Dómine, ne in furóre tuo árguas me, * neque in ira tua corrípias me.<br/>\n37:3 Quóniam sagíttæ tuæ infíxæ sunt mihi: * et confirmásti super me manum tuam.<br/>\n37:4 Non est sánitas in carne mea a fácie iræ tuæ: * non est pax óssibus meis a fácie peccatórum meórum.<br/>\n37:5 Quóniam iniquitátes meæ supergréssæ sunt caput meum: * et sicut onus grave gravátæ sunt super me.<br/>\n37:6 Putruérunt et corrúptæ sunt cicatríces meæ, * a fácie insipiéntiæ meæ.<br/>\n37:7 Miser factus sum, et curvátus sum usque in finem: * tota die contristátus ingrediébar.<br/>\n37:8 Quóniam lumbi mei impléti sunt illusiónibus: * et non est sánitas in carne mea.<br/>\n37:9 Afflíctus sum, et humiliátus sum nimis: * rugiébam a gémitu cordis mei.<br/>\n37:10 Dómine, ante te omne desidérium meum: * et gémitus meus a te non est abscónditus.<br/>\n37:11 Cor meum conturbátum est, derelíquit me virtus mea: * et lumen oculórum meórum, et ipsum non est mecum.<br/>\n37:12 Amíci mei, et próximi mei * advérsum me appropinquavérunt, et stetérunt.<br/>\n37:12 Et qui juxta me erant, de longe stetérunt: * et vim faciébant qui quærébant ánimam meam.<br/>\n37:13 Et qui inquirébant mala mihi, locúti sunt vanitátes: * et dolos tota die meditabántur.<br/>\n37:14 Ego autem tamquam surdus non audiébam: * et sicut mutus non apériens os suum.<br/>\n37:15 Et factus sum sicut homo non áudiens: * et non habens in ore suo redargutiónes.<br/>\n37:16 Quóniam in te, Dómine, sperávi: * tu exáudies me, Dómine, Deus meus.<br/>\n37:17 Quia dixi: Nequándo supergáudeant mihi inimíci mei: * et dum commovéntur pedes mei, super me magna locúti sunt.<br/>\n37:18 Quóniam ego in flagélla parátus sum: * et dolor meus in conspéctu meo semper.<br/>\n37:19 Quóniam iniquitátem meam annuntiábo: * et cogitábo pro peccáto meo.<br/>\n37:20 Inimíci autem mei vivunt, et confirmáti sunt super me: * et multiplicáti sunt qui odérunt me iníque.<br/>\n37:21 Qui retríbuunt mala pro bonis, detrahébant mihi: * quóniam sequébar bonitátem.<br/>\n37:22 Ne derelínquas me, Dómine, Deus meus: * ne discésseris a me.<br/>\n37:23 Inténde in adjutórium meum, * Dómine, Deus, salútis meæ.<br/>\nGloria omittitur<br/>\nAnt. Vim faciébant, qui quærébant ánimam meam.<br/>\n",
      "id": "do-1962-2026-04-03-matutinum-012",
      "raw": "!Nocturnus II\nAnt. Vim faciébant, * qui quærébant ánimam meam.\n&psalm(37)\nAnt. Vim faciébant, qui quærébant ánimam meam.\n"
    },
    {
      "html": "Ant. Confundántur * et revereántur, qui quærunt ánimam meam, ut áuferant eam.<br/>\nPsalmus 39 [5]<br/>\n39:2 Exspéctans exspectávi Dóminum, * et inténdit mihi.<br/>\n39:3 Et exaudívit preces meas: * et edúxit me de lacu misériæ, et de luto fæcis.<br/>\n39:3 Et státuit super petram pedes meos: * et diréxit gressus meos.<br/>\n39:4 Et immísit in os meum cánticum novum, * carmen Deo nostro.<br/>\n39:4 Vidébunt multi, et timébunt: * et sperábunt in Dómino.<br/>\n39:5 Beátus vir, cujus est nomen Dómini spes ejus: * et non respéxit in vanitátes et insánias falsas.<br/>\n39:6 Multa fecísti tu, Dómine, Deus meus, mirabília tua: * et cogitatiónibus tuis non est qui símilis sit tibi.<br/>\n39:6 Annuntiávi et locútus sum: * multiplicáti sunt super númerum.<br/>\n39:7 Sacrifícium et oblatiónem noluísti: * aures autem perfecísti mihi.<br/>\n39:7 Holocáustum et pro peccáto non postulásti: * tunc dixi: Ecce, vénio.<br/>\n39:8 In cápite libri scriptum est de me ut fácerem voluntátem tuam: * Deus meus, vólui, et legem tuam in médio cordis mei.<br/>\n39:10 Annuntiávi justítiam tuam in ecclésia magna, * ecce, lábia mea non prohibébo: Dómine, tu scisti.<br/>\n39:11 Justítiam tuam non abscóndi in corde meo: * veritátem tuam et salutáre tuum dixi.<br/>\n39:11 Non abscóndi misericórdiam tuam et veritátem tuam * a concílio multo.<br/>\n39:12 Tu autem, Dómine, ne longe fácias miseratiónes tuas a me: * misericórdia tua et véritas tua semper suscepérunt me.<br/>\n39:13 Quóniam circumdedérunt me mala, quorum non est númerus: * comprehendérunt me iniquitátes meæ, et non pótui ut vidérem.<br/>\n39:13 Multiplicátæ sunt super capíllos cápitis mei: * et cor meum derelíquit me.<br/>\n39:14 Compláceat tibi, Dómine, ut éruas me: * Dómine, ad adjuvándum me réspice.<br/>\n39:15 Confundántur et revereántur simul, qui quærunt ánimam meam, * ut áuferant eam.<br/>\n39:15 Convertántur retrórsum, et revereántur, * qui volunt mihi mala.<br/>\n39:16 Ferant conféstim confusiónem suam, * qui dicunt mihi: Euge, euge.<br/>\n39:17 Exsúltent et læténtur super te omnes quæréntes te: * et dicant semper: Magnificétur Dóminus: qui díligunt salutáre tuum.<br/>\n39:18 Ego autem mendícus sum, et pauper: * Dóminus sollícitus est mei.<br/>\n39:18 Adjútor meus, et protéctor meus tu es: * Deus meus, ne tardáveris.<br/>\nGloria omittitur<br/>\nAnt. Confundántur et revereántur, qui quærunt ánimam meam, ut áuferant eam.<br/>\n",
      "id": "do-1962-2026-04-03-matutinum-013",
      "raw": "Ant. Confundántur * et revereántur, qui quærunt ánimam meam, ut áuferant eam.\n&psalm(39)\nAnt. Confundántur et revereántur, qui quærunt ánimam meam, ut áuferant eam.\n"
    },
    {
      "html": "Ant. Aliéni * insurrexérunt in me, et fortes quæsiérunt ánimam meam.<br/>\nPsalmus 53 [6]<br/>\n53:3 Deus, in nómine tuo salvum me fac: * et in virtúte tua júdica me.<br/>\n53:4 Deus, exáudi oratiónem meam: * áuribus pércipe verba oris mei.<br/>\n53:5 Quóniam aliéni insurrexérunt advérsum me, et fortes quæsiérunt ánimam meam: * et non proposuérunt Deum ante conspéctum suum.<br/>\n53:6 Ecce enim, Deus ádjuvat me: * et Dóminus suscéptor est ánimæ meæ.<br/>\n53:7 Avérte mala inimícis meis: * et in veritáte tua dispérde illos.<br/>\n53:8 Voluntárie sacrificábo tibi, * et confitébor nómini tuo, Dómine: quóniam bonum est:<br/>\n53:9 Quóniam ex omni tribulatióne eripuísti me: * et super inimícos meos despéxit óculus meus.<br/>\nGloria omittitur<br/>\nAnt. Aliéni insurrexérunt in me, et fortes quæsiérunt ánimam meam.<br/>\n",
      "id": "do-1962-2026-04-03-matutinum-014",
      "raw": "Ant. Aliéni * insurrexérunt in me, et fortes quæsiérunt ánimam meam.\n&psalm(53)\nAnt. Aliéni insurrexérunt in me, et fortes quæsiérunt ánimam meam.\n"
    },
    {
      "html": "℣. Insurrexérunt in me testes iníqui.<br/>\n℟. Et mentíta est iníquitas sibi.<br/>\n",
      "id": "do-1962-2026-04-03-matutinum-015",
      "raw": "V. Insurrexérunt in me testes iníqui.\nR. Et mentíta est iníquitas sibi.\n"
    },
    {
      "html": "<span class='nigra'>Pater Noster</span> dicitur totum secreto.<br/>\nPater noster, qui es in cælis, sanctificétur nomen tuum: advéniat regnum tuum: fiat volúntas tua, sicut in cælo et in terra. Panem nostrum cotidiánum da nobis hódie: et dimítte nobis débita nostra, sicut et nos dimíttimus debitóribus nostris: et ne nos indúcas in tentatiónem: sed líbera nos a malo. Amen.<br/>\n",
      "id": "do-1962-2026-04-03-matutinum-016",
      "raw": "$Pater totum secreto\n"
    },
    {
      "html": "<br/>\nLectio 4<br/>\nEx tractátu sancti Augustíni Epíscopi super Psalmos<br/>\nIn Psalm 63 ad versum 2<br/>\nProtexísti me, Deus, a convéntu malignántium, a multitúdine operántium iniquitátem. Jam ipsum caput nostrum intueámur. Multi Mártyres tália passi sunt, sed nihil sic elúcet, quómodo caput Mártyrum: ibi mélius intuémur, quod illi expérti sunt. Protéctus est a multitúdine malignántium, protegénte se Deo, protegénte carnem suam ipso Fílio, et hómine, quem gerébat: quia fílius hóminis est, et Fílius Dei est. Fílius Dei, propter formam Dei: fílius hóminis, propter formam servi, habens in potestáte pónere ánimam suam, et recípere eam. Quid ei potuérunt fácere inimíci? Occidérunt corpus, ánimam non occidérunt. Inténdite. Parum ergo erat, Dóminum hortári Mártyres verbo, nisi firmáret exémplo.<br/>\n_<br/>\n℟. Tamquam ad latrónem exístis cum gládiis et fústibus comprehéndere me:<br/>\n* Cotídie apud vos eram in templo docens, et non me tenuístis: et ecce flagellátum dúcitis ad crucifigéndum.<br/>\n℣. Cumque injecíssent manus in Jesum, et tenuíssent eum, dixit ad eos.<br/>\n℟. Cotídie apud vos eram in templo docens, et non me tenuístis: et ecce flagellátum dúcitis ad crucifigéndum.<br/>\n",
      "id": "do-1962-2026-04-03-matutinum-017",
      "raw": "&lectio(4)\n"
    },
    {
      "html": "<br/>\nLectio 5<br/>\nNostis qui convéntus erat malignántium Judæórum, et quæ multitúdo erat operántium iniquitátem. Quam iniquitátem? Quia voluérunt occídere Dóminum Jesum Christum. Tanta ópera bona, inquit, osténdi vobis: propter quod horum me vultis occídere? Pértulit omnes infírmos eórum, curávit omnes lánguidos eórum, prædicávit regnum cælórum, non tácuit vítia eórum, ut ipsa pótius eis displicérent, non médicus, a quo sanabántur. His ómnibus curatiónibus ejus ingráti, tamquam multa febre phrenétici, insaniéntes in médicum, qui vénerat curáre eos, excogitavérunt consílium perdéndi eum: tamquam ibi voléntes probáre, utrum vere homo sit, qui mori possit, an áliquid super hómines sit, et mori se non permíttat. Verbum ipsórum agnóscimus in Sapiéntia Salomónis: Morte turpíssima, ínquiunt, condemnémus eum. Interrogémus eum: erit enim respéctus in sermónibus illíus. Si enim vere Fílius Dei est, líberet eum.<br/>\n_<br/>\n℟. Ténebræ factæ sunt, dum crucifixíssent Jesum Judǽi: et circa horam nonam exclamávit Jesus voce magna: Deus meus, ut quid me dereliquísti?<br/>\n* Et inclináto cápite, emísit spíritum.<br/>\n℣. Exclámans Jesus voce magna, ait: Pater, in manus tuas comméndo spíritum meum.<br/>\n℟. Et inclináto cápite, emísit spíritum.<br/>\n",
      "id": "do-1962-2026-04-03-matutinum-018",
      "raw": "&lectio(5)\n"
    },
    {
      "html": "<br/>\nLectio 6<br/>\nExacuérunt tamquam gládium linguas suas. Non dicant Judǽi: Non occídimus Christum. Etenim proptérea eum dedérunt júdici Piláto, ut quasi ipsi a morte ejus videréntur immúnes. Nam cum dixísset eis Pilátus: Vos eum occídite: respondérunt, Nobis non licet occídere quemquam. Iniquitátem facínoris sui in júdicem hóminem refúndere volébant: sed numquid Deum júdicem fallébant? Quod fecit Pilátus, in eo ipso quod fecit, aliquántum párticeps fuit: sed in comparatióne illórum multo ipse innocéntior. Institit enim quantum pótuit, ut illum ex eórum mánibus liberáret: nam proptérea flagellátum prodúxit ad eos. Non persequéndo Dóminum flagellávit, sed eórum furóri satisfácere volens: ut vel sic jam mitéscerent, et desínerent velle occídere, cum flagellátum vidérent. Fecit et hoc. At ubi perseveravérunt, nostis illum lavísse manus, et dixísse, quod ipse non fecísset, mundum se esse a morte illíus. Fecit tamen. Sed si reus, quia fecit vel invítus: illi innocéntes, qui coëgérunt ut fáceret? Nullo modo. Sed ille dixit in eum senténtiam, et jussit eum crucifígi, et quasi ipse occídit: et vos, o Judǽi, occidístis. Unde occidístis? Gládio linguæ: acuístis enim linguas vestras. Et quando percussístis, nisi quando clamástis: Crucifíge, crucifíge?<br/>\n_<br/>\n℟. Animam meam diléctam trádidi in manus iniquórum, et facta est mihi heréditas mea sicut leo in silva: dedit contra me voces adversárius, dicens: Congregámini, et properáte ad devorándum illum: posuérunt me in desérto solitúdinis, et luxit super me omnis terra:<br/>\n* Quia non est invéntus qui me agnósceret, et fáceret bene.<br/>\n℣. Insurrexérunt in me viri absque misericórdia, et non pepercérunt ánimæ meæ.<br/>\n℟. Quia non est invéntus qui me agnósceret, et fáceret bene.<br/>\nGloria omittitur<br/>\n℟. Animam meam diléctam trádidi in manus iniquórum, et facta est mihi heréditas mea sicut leo in silva: dedit contra me voces adversárius, dicens: Congregámini, et properáte ad devorándum illum: posuérunt me in desérto solitúdinis, et luxit super me omnis terra: * Quia non est invéntus qui me agnósceret, et fáceret bene.<br/>\n",
      "id": "do-1962-2026-04-03-matutinum-019",
      "raw": "&lectio(6)\n"
    },
    {
      "html": "Nocturnus III<br/>\nAnt. Ab insurgéntibus in me * líbera me, Dómine, quia occupavérunt ánimam meam.<br/>\nPsalmus 58 [7]<br/>\n58:2 Éripe me de inimícis meis, Deus meus: * et ab insurgéntibus in me líbera me.<br/>\n58:3 Éripe me de operántibus iniquitátem: * et de viris sánguinum salva me.<br/>\n58:4 Quia ecce cepérunt ánimam meam: * irruérunt in me fortes.<br/>\n58:5 Neque iníquitas mea, neque peccátum meum, Dómine: * sine iniquitáte cucúrri, et diréxi.<br/>\n58:6 Exsúrge in occúrsum meum, et vide: * et tu, Dómine, Deus virtútum, Deus Israël,<br/>\n58:6 Inténde ad visitándas omnes gentes: * non misereáris ómnibus, qui operántur iniquitátem.<br/>\n58:7 Converténtur ad vésperam: et famem patiéntur ut canes, * et circuíbunt civitátem.<br/>\n58:8 Ecce, loquéntur in ore suo, et gládius in lábiis eórum: * quóniam quis audívit?<br/>\n58:9 Et tu, Dómine, deridébis eos: * ad níhilum dedúces omnes gentes.<br/>\n58:10 Fortitúdinem meam ad te custódiam, quia, Deus, suscéptor meus es: * Deus meus, misericórdia ejus prævéniet me.<br/>\n58:12 Deus osténdet mihi super inimícos meos, ne occídas eos: * nequándo obliviscántur pópuli mei.<br/>\n58:12 Dispérge illos in virtúte tua: * et depóne eos, protéctor meus, Dómine:<br/>\n58:13 Delíctum oris eórum, sermónem labiórum ipsórum: * et comprehendántur in supérbia sua.<br/>\n58:13 Et de exsecratióne et mendácio annuntiabúntur in consummatióne: * in ira consummatiónis, et non erunt.<br/>\n58:14 Et scient quia Deus dominábitur Jacob: * et fínium terræ.<br/>\n58:15 Converténtur ad vésperam: et famem patiéntur ut canes, * et circuíbunt civitátem.<br/>\n58:16 Ipsi dispergéntur ad manducándum: * si vero non fúerint saturáti, et murmurábunt.<br/>\n58:17 Ego autem cantábo fortitúdinem tuam: * et exsultábo mane misericórdiam tuam.<br/>\n58:17 Quia factus es suscéptor meus, * et refúgium meum, in die tribulatiónis meæ.<br/>\n58:18 Adjútor meus, tibi psallam, quia, Deus, suscéptor meus es: * Deus meus, misericórdia mea.<br/>\nGloria omittitur<br/>\nAnt. Ab insurgéntibus in me líbera me, Dómine, quia occupavérunt ánimam meam.<br/>\n",
      "id": "do-1962-2026-04-03-matutinum-020",
      "raw": "!Nocturnus III\nAnt. Ab insurgéntibus in me * líbera me, Dómine, quia occupavérunt ánimam meam.\n&psalm(58)\nAnt. Ab insurgéntibus in me líbera me, Dómine, quia occupavérunt ánimam meam.\n"
    },
    {
      "html": "Ant. Longe fecísti * notos meos a me: tráditus sum, et non egrediébar.<br/>\nPsalmus 87 [8]<br/>\n87:2 Dómine, Deus salútis meæ: * in die clamávi, et nocte coram te.<br/>\n87:3 Intret in conspéctu tuo orátio mea: * inclína aurem tuam ad precem meam:<br/>\n87:4 Quia repléta est malis ánima mea: * et vita mea inférno appropinquávit.<br/>\n87:5 Æstimátus sum cum descendéntibus in lacum: * factus sum sicut homo sine adjutório, inter mórtuos liber.<br/>\n87:6 Sicut vulneráti dormiéntes in sepúlcris, quorum non es memor ámplius: * et ipsi de manu tua repúlsi sunt.<br/>\n87:7 Posuérunt me in lacu inferióri: * in tenebrósis, et in umbra mortis.<br/>\n87:8 Super me confirmátus est furor tuus: * et omnes fluctus tuos induxísti super me.<br/>\n87:9 Longe fecísti notos meos a me: * posuérunt me abominatiónem sibi.<br/>\n87:9 Tráditus sum, et non egrediébar: * óculi mei languérunt præ inópia.<br/>\n87:10 Clamávi ad te, Dómine, tota die: * expándi ad te manus meas.<br/>\n87:11 Numquid mórtuis fácies mirabília: * aut médici suscitábunt, et confitebúntur tibi?<br/>\n87:12 Numquid narrábit áliquis in sepúlcro misericórdiam tuam, * et veritátem tuam in perditióne?<br/>\n87:13 Numquid cognoscéntur in ténebris mirabília tua, * et justítia tua in terra obliviónis?<br/>\n87:14 Et ego ad te, Dómine, clamávi: * et mane orátio mea prævéniet te.<br/>\n87:15 Ut quid, Dómine, repéllis oratiónem meam: * avértis fáciem tuam a me?<br/>\n87:16 Pauper sum ego, et in labóribus a juventúte mea: * exaltátus autem, humiliátus sum et conturbátus.<br/>\n87:17 In me transiérunt iræ tuæ: * et terróres tui conturbavérunt me.<br/>\n87:18 Circumdedérunt me sicut aqua tota die: * circumdedérunt me simul.<br/>\n87:19 Elongásti a me amícum et próximum: * et notos meos a miséria.<br/>\nGloria omittitur<br/>\nAnt. Longe fecísti notos meos a me: tráditus sum, et non egrediébar.<br/>\n",
      "id": "do-1962-2026-04-03-matutinum-021",
      "raw": "Ant. Longe fecísti * notos meos a me: tráditus sum, et non egrediébar.\n&psalm(87)\nAnt. Longe fecísti notos meos a me: tráditus sum, et non egrediébar.\n"
    },
    {
      "html": "Ant. Captábunt * in ánimam justi, et sánguinem innocéntem condemnábunt.<br/>\nPsalmus 93 [9]<br/>\n93:1 Deus ultiónum Dóminus: * Deus ultiónum líbere egit.<br/>\n93:2 Exaltáre, qui júdicas terram: * redde retributiónem supérbis.<br/>\n93:3 Úsquequo peccatóres, Dómine, * úsquequo peccatóres gloriabúntur:<br/>\n93:4 Effabúntur, et loquéntur iniquitátem: * loquéntur omnes, qui operántur injustítiam?<br/>\n93:5 Pópulum tuum, Dómine, humiliavérunt: * et hereditátem tuam vexavérunt.<br/>\n93:6 Víduam, et ádvenam interfecérunt: * et pupíllos occidérunt.<br/>\n93:7 Et dixérunt: Non vidébit Dóminus, * nec intélleget Deus Jacob.<br/>\n93:8 Intellégite, insipiéntes in pópulo: * et stulti, aliquándo sápite.<br/>\n93:9 Qui plantávit aurem, non áudiet? * aut qui finxit óculum, non consíderat?<br/>\n93:10 Qui córripit gentes, non árguet: * qui docet hóminem sciéntiam?<br/>\n93:11 Dóminus scit cogitatiónes hóminum, * quóniam vanæ sunt.<br/>\n93:12 Beátus homo, quem tu erudíeris, Dómine: * et de lege tua docúeris eum,<br/>\n93:13 Ut mítiges ei a diébus malis: * donec fodiátur peccatóri fóvea.<br/>\n93:14 Quia non repéllet Dóminus plebem suam: * et hereditátem suam non derelínquet.<br/>\n93:15 Quoadúsque justítia convertátur in judícium: * et qui juxta illam omnes qui recto sunt corde.<br/>\n93:16 Quis consúrget mihi advérsus malignántes? * aut quis stabit mecum advérsus operántes iniquitátem?<br/>\n93:17 Nisi quia Dóminus adjúvit me: * paulo minus habitásset in inférno ánima mea.<br/>\n93:18 Si dicébam: Motus est pes meus: * misericórdia tua, Dómine, adjuvábat me.<br/>\n93:19 Secúndum multitúdinem dolórum meórum in corde meo: * consolatiónes tuæ lætificavérunt ánimam meam.<br/>\n93:20 Numquid adhǽret tibi sedes iniquitátis: * qui fingis labórem in præcépto?<br/>\n93:21 Captábunt in ánimam justi: * et sánguinem innocéntem condemnábunt.<br/>\n93:22 Et factus est mihi Dóminus in refúgium: * et Deus meus in adjutórium spei meæ.<br/>\n93:23 Et reddet illis iniquitátem ipsórum: et in malítia eórum dispérdet eos: * dispérdet illos Dóminus, Deus noster.<br/>\nGloria omittitur<br/>\nAnt. Captábunt in ánimam justi, et sánguinem innocéntem condemnábunt.<br/>\n",
      "id": "do-1962-2026-04-03-matutinum-022",
      "raw": "Ant. Captábunt * in ánimam justi, et sánguinem innocéntem condemnábunt.\n&psalm(93)\nAnt. Captábunt in ánimam justi, et sánguinem innocéntem condemnábunt.\n"
    },
    {
      "html": "℣. Locúti sunt advérsum me lingua dolósa.<br/>\n℟. Et sermónibus ódii circumdedérunt me, et expugnavérunt me gratis.<br/>\n",
      "id": "do-1962-2026-04-03-matutinum-023",
      "raw": "V. Locúti sunt advérsum me lingua dolósa.\nR. Et sermónibus ódii circumdedérunt me, et expugnavérunt me gratis.\n"
    },
    {
      "html": "<span class='nigra'>Pater Noster</span> dicitur totum secreto.<br/>\nPater noster, qui es in cælis, sanctificétur nomen tuum: advéniat regnum tuum: fiat volúntas tua, sicut in cælo et in terra. Panem nostrum cotidiánum da nobis hódie: et dimítte nobis débita nostra, sicut et nos dimíttimus debitóribus nostris: et ne nos indúcas in tentatiónem: sed líbera nos a malo. Amen.<br/>\n",
      "id": "do-1962-2026-04-03-matutinum-024",
      "raw": "$Pater totum secreto\n"
    },
    {
      "html": "<br/>\nLectio 7<br/>\nDe Epístola beáti Pauli Apóstoli ad Hebrǽos<br/>\nHeb 4:11-15<br/>\n11 Festinémus íngredi in illam réquiem: ut ne in idípsum quis íncidat incredulitátis exémplum.<br/>\n12 Vivus est enim sermo Dei, et éfficax et penetrabílior omni gládio ancípiti: et pertíngens usque ad divisiónem ánimæ ac spíritus, compágum quoque ac medullárum, et discrétor cogitatiónum et intentiónum cordis.<br/>\n13 Et non est ulla creatúra invisíbilis in conspéctu ejus: ómnia autem nuda et apérta sunt óculis ejus, ad quem nobis sermo.<br/>\n14 Habéntes ergo Pontíficem magnum, qui penetrávit cælos, Jesum Fílium Dei: teneámus confessiónem.<br/>\n15 Non enim habémus Pontíficem, qui non possit cómpati infirmitátibus nostris: tentátum autem per ómnia pro similitúdine absque peccáto.<br/>\n_<br/>\n℟. Tradidérunt me in manus impiórum, et inter iníquos projecérunt me, et non pepercérunt ánimæ meæ: congregáti sunt advérsum me fortes:<br/>\n* Et sicut gigántes stetérunt contra me.<br/>\n℣. Aliéni insurrexérunt advérsum me, et fortes quæsiérunt ánimam meam.<br/>\n℟. Et sicut gigántes stetérunt contra me.<br/>\n",
      "id": "do-1962-2026-04-03-matutinum-025",
      "raw": "&lectio(7)\n"
    },
    {
      "html": "<br/>\nLectio 8<br/>\nHeb 4:16; 5:1-3<br/>\n16 Adeámus ergo cum fidúcia ad thronum grátiæ: ut misericórdiam consequámur, et grátiam inveniámus in auxílio opportúno.<br/>\n1 Omnis namque Póntifex ex homínibus assúmptus, pro homínibus constitúitur in iis, quæ sunt ad Deum, ut ófferat dona, et sacrifícia pro peccátis:<br/>\n2 Qui condolére possit iis, qui ignórant et errant: quóniam et ipse circúmdatus est infirmitáte:<br/>\n3 Et proptérea debet quemádmodum pro pópulo, ita étiam pro semetípso offérre pro peccátis.<br/>\n_<br/>\n℟. Jesum trádidit ímpius summis princípibus sacerdótum, et senióribus pópuli:<br/>\n* Petrus autem sequebátur eum a longe, ut vidéret finem.<br/>\n℣. Adduxérunt autem eum ad Cáipham príncipem sacerdótum, ubi scribæ et pharisǽi convénerant.<br/>\n℟. Petrus autem sequebátur eum a longe, ut vidéret finem.<br/>\n",
      "id": "do-1962-2026-04-03-matutinum-026",
      "raw": "&lectio(8)\n"
    },
    {
      "html": "<br/>\nLectio 9<br/>\nHeb 5:4-10<br/>\n4 Nec quisquam sumit sibi honórem, sed qui vocátur a Deo, tamquam Aaron.<br/>\n5 Sic et Christus non semetípsum clarificávit ut Póntifex fíeret, sed qui locútus est ad eum: Fílius meus es tu, ego hódie génui te.<br/>\n6 Quemádmodum et in álio loco dicit: Tu es sacérdos in ætérnum, secúndum órdinem Melchísedech.<br/>\n7 Qui in diébus carnis suæ preces, supplicationésque ad eum, qui possit illum salvum fácere a morte, cum clamóre válido et lácrimis ófferens, exaudítus est pro sua reveréntia.<br/>\n8 Et quidem cum esset Fílius Dei, dídicit ex iis, quæ passus est, obediéntiam:<br/>\n9 Et consummátus, factus est ómnibus obtemperántibus sibi causa salútis ætérnæ,<br/>\n10 Appellátus a Deo Póntifex juxta órdinem Melchísedech.<br/>\n_<br/>\n℟. Caligavérunt óculi mei a fletu meo: quia elongátus est a me, qui consolabátur me: Vidéte omnes pópuli,<br/>\n* Si est dolor símilis sicut dolor meus.<br/>\n℣. O vos omnes, qui transítis per viam, atténdite et vidéte.<br/>\n℟. Si est dolor símilis sicut dolor meus.<br/>\nGloria omittitur<br/>\n℟. Caligavérunt óculi mei a fletu meo: quia elongátus est a me, qui consolabátur me: Vidéte omnes pópuli, * Si est dolor símilis sicut dolor meus.<br/>\n",
      "id": "do-1962-2026-04-03-matutinum-027",
      "raw": "&lectio(9)\n"
    },
    {
      "html": "Reliqua omittuntur, nisi %Laudes% separandæ sint.<br/>\n",
      "id": "do-1962-2026-04-03-matutinum-028",
      "raw": "$rubrica Matutinum\n"
    },
    {
      "html": "Oratio {ex Proprio de Tempore}\n<br/>\nRéspice, quǽsumus, Dómine, super hanc famíliam tuam, pro qua Dóminus noster Jesus Christus non dubitávit mánibus tradi nocéntium, et crucis subíre torméntum:<br/>\nEt sub silentio concluditur<br/>\nQui tecum vivit et regnat in unitáte Spíritus Sancti, Deus, per ómnia sǽcula sæculórum.<br/>\n℟. Amen.<br/>\n",
      "id": "do-1962-2026-04-03-matutinum-029",
      "raw": "#Oratio{ex Proprio de Tempore}\nv. Réspice, quǽsumus, Dómine, super hanc famíliam tuam, pro qua Dóminus noster Jesus Christus non dubitávit mánibus tradi nocéntium, et crucis subíre torméntum:\n!Et sub silentio concluditur\n$Qui tecum\n\n"
    },
    {
      "html": "Conclusio{omittitur}<br/>\n",
      "id": "do-1962-2026-04-03-matutinum-030",
      "raw": "#Conclusio{omittitur}\n"
    }
  ],
  "upstreamCommit": "515a213f79951c563be4f599ca591c63aa63bb6d",
  "warnings": []
}
